{"name":"colasa","description":"stencil, graffiti,street, art,painting,spray,taiwan,asian,taipei,colasa,artist,skateboard,tattoo,skate,fashion","url":"http://colasa.bigcartel.com","website":"","products_count":5,"currency":{"id":1,"sign":"$","name":"U.S. Dollar","code":"USD"},"country":{"id":39,"name":"Taiwan","code":"TW"},"pages":[{"name":"FAQ","permalink":"faq"},{"name":"About","permalink":"about"}],"categories":[{"id":1663332,"permalink":"canvas","url":"/category/canvas","name":"Canvas"},{"id":1663333,"permalink":"skateboard","url":"/category/skateboard","name":"Skateboard"},{"id":1663334,"permalink":"others","url":"/category/others","name":"Others"}],"artists":[]}