{"name":"Steve Grimmett","description":null,"url":"http://stevegrimmett.bigcartel.com","website":"http://www.stevegrimmett.co.uk","products_count":5,"currency":{"id":5,"sign":"&pound;","name":"Pound Sterling","code":"GBP"},"country":{"id":43,"name":"United States","code":"US"},"pages":[],"categories":[{"id":240342,"permalink":"cds","url":"/category/cds","name":"CDs"},{"id":240343,"permalink":"hats","url":"/category/hats","name":"Hats"},{"id":240344,"permalink":"posters","url":"/category/posters","name":"Posters"},{"id":240345,"permalink":"tees","url":"/category/tees","name":"Tees"},{"id":240363,"permalink":"dvds","url":"/category/dvds","name":"DVDs"}],"artists":[]}