{"name":"Forte Fortuna","description":"Based in Baltimore, Forte Fortuna is a purveyor of quality handmade accessories. ","url":"http://fortefortuna.bigcartel.com","website":"","products_count":25,"currency":{"id":1,"sign":"$","name":"U.S. Dollar","code":"USD"},"country":{"id":43,"name":"United States","code":"US"},"pages":[],"categories":[{"id":3412355,"permalink":"cds","url":"/category/cds","name":"CDs"},{"id":3412357,"permalink":"hats","url":"/category/hats","name":"Hats"},{"id":3412359,"permalink":"posters","url":"/category/posters","name":"Posters"},{"id":3412361,"permalink":"tees","url":"/category/tees","name":"Tees"},{"id":3412479,"permalink":"bracelets","url":"/category/bracelets","name":"Bracelets"},{"id":3412481,"permalink":"jewelry","url":"/category/jewelry","name":"Jewelry"}],"artists":[]}