[{"id":6787673,"name":"We Run This School ","permalink":"we-run-this-school","position":1,"price":14.0,"default_price":14.0,"tax":0.0,"url":"/product/we-run-this-school","status":"active","on_sale":true,"created_at":"2012-07-25T09:59:06.000Z","description":"In honor of Class of 2012\r\n","options":[{"id":21552977,"name":"S","price":14.0,"sold_out":false,"has_custom_price":false},{"id":21552979,"name":"M","price":14.0,"sold_out":false,"has_custom_price":false},{"id":21552981,"name":"L","price":14.0,"sold_out":false,"has_custom_price":false}],"shipping":[{"amount_alone":5.5,"amount_with_others":0.0,"country":{"id":43,"name":"United States","code":"US"}}],"images":[{"url":"http://images.cdn.bigcartel.com/bigcartel/product_images/66640861/-/DSC_2384.jpg","secure_url":"https://d1j5c7u4mzbpxw.cloudfront.net/bigcartel/product_images/66640861/-/DSC_2384.jpg","width":669,"height":1000}],"artists":[],"categories":[]}]