{"name":"Officer Down Webstore","description":"Official web-store of punk/hardcore band OFFICER DOWN!","url":"http://officerdown.bigcartel.com","website":"http://www.facebook.com/officerdownuk","products_count":5,"currency":{"id":5,"sign":"&pound;","name":"Pound Sterling","code":"GBP"},"country":{"id":42,"name":"United Kingdom","code":"GB"},"pages":[],"categories":[{"id":2244197,"permalink":"cds","url":"/category/cds","name":"CDs"},{"id":2244199,"permalink":"hats","url":"/category/hats","name":"Hats"},{"id":2244201,"permalink":"posters","url":"/category/posters","name":"Posters"},{"id":2244203,"permalink":"tees","url":"/category/tees","name":"Tees"},{"id":2244285,"permalink":"patches","url":"/category/patches","name":"Patches"},{"id":2244289,"permalink":"vinyl","url":"/category/vinyl","name":"Vinyl"},{"id":2570113,"permalink":"hoodies","url":"/category/hoodies","name":"Hoodies"}],"artists":[]}