{"name":"SLICKSYMBOLAPPAREL","description":"WHERE YOUR FIRST IMPRESSIONS ARE NEVER TO WORRY ABOUT!","url":"http://slicksymbolapparel.bigcartel.com","website":null,"products_count":15,"currency":{"id":1,"sign":"$","name":"U.S. Dollar","code":"USD"},"country":{"id":43,"name":"United States","code":"US"},"pages":[],"categories":[{"id":4939630,"permalink":"hats","url":"/category/hats","name":"Hats"},{"id":4939633,"permalink":"prints","url":"/category/prints","name":"Prints"},{"id":4939636,"permalink":"tees","url":"/category/tees","name":"Tees"},{"id":5022295,"permalink":"money","url":"/category/money","name":"Money"},{"id":5065951,"permalink":"mens-tanks","url":"/category/mens-tanks","name":"Mens Tanks"},{"id":5122254,"permalink":"nba-jerseys","url":"/category/nba-jerseys","name":"Nba jerseys"},{"id":5696031,"permalink":"womens-tanks","url":"/category/womens-tanks","name":"Womens tanks"},{"id":6077451,"permalink":"nfl-jerseys","url":"/category/nfl-jerseys","name":"Nfl Jerseys"},{"id":6161988,"permalink":"kids-snapbacks","url":"/category/kids-snapbacks","name":"Kids Snapbacks"},{"id":6361377,"permalink":"3-4-raglan-tees","url":"/category/3-4-raglan-tees","name":"3/4 Raglan tees"},{"id":6366693,"permalink":"womens-tops","url":"/category/womens-tops","name":"Womens tops"},{"id":6749898,"permalink":"iphone-case","url":"/category/iphone-case","name":"Iphone case"}],"artists":[]}