[{"id":15300687,"name":"FADE K-TOWN JACKET ","permalink":"fade-k-town-jacket","position":1,"price":54.0,"default_price":54.0,"tax":0.0,"url":"/product/fade-k-town-jacket","status":"active","on_sale":false,"created_at":"2013-12-03T16:48:02.000Z","description":"","options":[{"id":49745436,"name":"Default","price":54.0,"sold_out":false,"has_custom_price":false}],"shipping":[{"amount_alone":4.0,"amount_with_others":2.0,"country":{"id":42,"name":"United Kingdom","code":"GB"}},{"amount_alone":7.0,"amount_with_others":3.5}],"images":[{"url":"http://images.cdn.bigcartel.com/bigcartel/product_images/128740578/-/fadekwayjacket.jpg","secure_url":"https://d1j5c7u4mzbpxw.cloudfront.net/bigcartel/product_images/128740578/-/fadekwayjacket.jpg","width":1744,"height":3504}],"artists":[],"categories":[]},{"id":15300669,"name":"BLACK K-TOWN JACKET","permalink":"black-k-town-jacket","position":2,"price":54.0,"default_price":54.0,"tax":0.0,"url":"/product/black-k-town-jacket","status":"active","on_sale":false,"created_at":"2013-12-03T16:47:06.000Z","description":"","options":[{"id":49745352,"name":"Default","price":54.0,"sold_out":false,"has_custom_price":false}],"shipping":[{"amount_alone":4.0,"amount_with_others":3.0,"country":{"id":42,"name":"United Kingdom","code":"GB"}},{"amount_alone":7.5,"amount_with_others":3.0}],"images":[{"url":"http://images.cdn.bigcartel.com/bigcartel/product_images/128740518/-/blkkwayjacket.jpg","secure_url":"https://d1j5c7u4mzbpxw.cloudfront.net/bigcartel/product_images/128740518/-/blkkwayjacket.jpg","width":1632,"height":3352}],"artists":[],"categories":[]},{"id":15300630,"name":"PINK K-TOWN BUCKET","permalink":"pink-k-town-bucket","position":3,"price":32.0,"default_price":32.0,"tax":0.0,"url":"/product/pink-k-town-bucket","status":"active","on_sale":false,"created_at":"2013-12-03T16:45:42.000Z","description":"","options":[{"id":49745148,"name":"Default","price":32.0,"sold_out":false,"has_custom_price":false}],"shipping":[{"amount_alone":3.5,"amount_with_others":2.0,"country":{"id":42,"name":"United Kingdom","code":"GB"}},{"amount_alone":7.0,"amount_with_others":3.0}],"images":[{"url":"http://images.cdn.bigcartel.com/bigcartel/product_images/128740419/-/pinkkwaybucket.jpg","secure_url":"https://d1j5c7u4mzbpxw.cloudfront.net/bigcartel/product_images/128740419/-/pinkkwaybucket.jpg","width":1696,"height":2752},{"url":"http://images.cdn.bigcartel.com/bigcartel/product_images/128740431/-/pinkkhat.jpeg","secure_url":"https://d1j5c7u4mzbpxw.cloudfront.net/bigcartel/product_images/128740431/-/pinkkhat.jpeg","width":600,"height":600}],"artists":[],"categories":[]},{"id":15300600,"name":"BLACK K-TOWN BUCKET","permalink":"black-k-town-bucket","position":4,"price":32.0,"default_price":32.0,"tax":0.0,"url":"/product/black-k-town-bucket","status":"active","on_sale":false,"created_at":"2013-12-03T16:44:20.000Z","description":"","options":[{"id":49744842,"name":"Default","price":32.0,"sold_out":false,"has_custom_price":false}],"shipping":[{"amount_alone":3.5,"amount_with_others":2.0,"country":{"id":42,"name":"United Kingdom","code":"GB"}},{"amount_alone":7.0,"amount_with_others":3.0}],"images":[{"url":"http://images.cdn.bigcartel.com/bigcartel/product_images/128740344/-/kwayhatblk.jpg","secure_url":"https://d1j5c7u4mzbpxw.cloudfront.net/bigcartel/product_images/128740344/-/kwayhatblk.jpg","width":1024,"height":1304},{"url":"http://images.cdn.bigcartel.com/bigcartel/product_images/128740323/-/blkkhat.jpg","secure_url":"https://d1j5c7u4mzbpxw.cloudfront.net/bigcartel/product_images/128740323/-/blkkhat.jpg","width":400,"height":534}],"artists":[],"categories":[]},{"id":14710161,"name":"BLACK TRACK TOP","permalink":"black-track-top","position":5,"price":34.0,"default_price":34.0,"tax":0.0,"url":"/product/black-track-top","status":"active","on_sale":false,"created_at":"2013-11-08T15:55:48.000Z","description":"BLACK TRACK TOP","options":[{"id":47657808,"name":"Default","price":34.0,"sold_out":false,"has_custom_price":false}],"shipping":[{"amount_alone":5.0,"amount_with_others":8.0,"country":{"id":42,"name":"United Kingdom","code":"GB"}},{"amount_alone":15.0,"amount_with_others":23.0}],"images":[{"url":"http://images.cdn.bigcartel.com/bigcartel/product_images/127228452/-/blktrackarms2.jpg","secure_url":"https://d1j5c7u4mzbpxw.cloudfront.net/bigcartel/product_images/127228452/-/blktrackarms2.jpg","width":1616,"height":2688},{"url":"http://images.cdn.bigcartel.com/bigcartel/product_images/127226865/-/blktracktop.jpg","secure_url":"https://d1j5c7u4mzbpxw.cloudfront.net/bigcartel/product_images/127226865/-/blktracktop.jpg","width":1040,"height":1784},{"url":"http://images.cdn.bigcartel.com/bigcartel/product_images/127226874/-/trackblkback.jpg","secure_url":"https://d1j5c7u4mzbpxw.cloudfront.net/bigcartel/product_images/127226874/-/trackblkback.jpg","width":1096,"height":1576}],"artists":[],"categories":[]},{"id":14710179,"name":"GREY TRACK TOP","permalink":"grey-track-top","position":6,"price":34.0,"default_price":34.0,"tax":0.0,"url":"/product/grey-track-top","status":"active","on_sale":false,"created_at":"2013-11-08T15:57:13.000Z","description":"GREY TRACK TOP","options":[{"id":47657841,"name":"Default","price":34.0,"sold_out":false,"has_custom_price":false}],"shipping":[{"amount_alone":5.0,"amount_with_others":8.0,"country":{"id":42,"name":"United Kingdom","code":"GB"}},{"amount_alone":15.0,"amount_with_others":23.0}],"images":[{"url":"http://images.cdn.bigcartel.com/bigcartel/product_images/127226928/-/greyarms.jpg","secure_url":"https://d1j5c7u4mzbpxw.cloudfront.net/bigcartel/product_images/127226928/-/greyarms.jpg","width":1920,"height":2624},{"url":"http://images.cdn.bigcartel.com/bigcartel/product_images/127226943/-/greytopback.jpg","secure_url":"https://d1j5c7u4mzbpxw.cloudfront.net/bigcartel/product_images/127226943/-/greytopback.jpg","width":1529,"height":1180}],"artists":[],"categories":[]},{"id":14710110,"name":"HTWN BLACK TEE","permalink":"htwn-black-tee","position":7,"price":29.0,"default_price":29.0,"tax":0.0,"url":"/product/htwn-black-tee","status":"active","on_sale":false,"created_at":"2013-11-08T15:52:21.000Z","description":"HTWN BLACK TEE","options":[{"id":47657640,"name":"Default","price":29.0,"sold_out":false,"has_custom_price":false}],"shipping":[{"amount_alone":4.0,"amount_with_others":7.0,"country":{"id":42,"name":"United Kingdom","code":"GB"}},{"amount_alone":12.0,"amount_with_others":18.0}],"images":[{"url":"http://images.cdn.bigcartel.com/bigcartel/product_images/127226781/-/blackteefront.jpg","secure_url":"https://d1j5c7u4mzbpxw.cloudfront.net/bigcartel/product_images/127226781/-/blackteefront.jpg","width":1464,"height":2528},{"url":"http://images.cdn.bigcartel.com/bigcartel/product_images/127226784/-/blkteeside.jpg","secure_url":"https://d1j5c7u4mzbpxw.cloudfront.net/bigcartel/product_images/127226784/-/blkteeside.jpg","width":1296,"height":2504}],"artists":[],"categories":[]},{"id":14710083,"name":"HTWN TEE GREY","permalink":"htwn-tee-grey","position":8,"price":29.0,"default_price":29.0,"tax":0.0,"url":"/product/htwn-tee-grey","status":"active","on_sale":false,"created_at":"2013-11-08T15:51:07.000Z","description":"HTWN TEE GREY","options":[{"id":47657601,"name":"Default","price":29.0,"sold_out":false,"has_custom_price":false}],"shipping":[{"amount_alone":4.0,"amount_with_others":7.0,"country":{"id":42,"name":"United Kingdom","code":"GB"}},{"amount_alone":12.0,"amount_with_others":18.0}],"images":[{"url":"http://images.cdn.bigcartel.com/bigcartel/product_images/127226742/-/greytee.jpg","secure_url":"https://d1j5c7u4mzbpxw.cloudfront.net/bigcartel/product_images/127226742/-/greytee.jpg","width":1832,"height":2720}],"artists":[],"categories":[]},{"id":14710131,"name":"HTWN WHITE TEE","permalink":"htwn-white-tee","position":9,"price":29.0,"default_price":29.0,"tax":0.0,"url":"/product/htwn-white-tee","status":"active","on_sale":false,"created_at":"2013-11-08T15:53:20.000Z","description":"HTWN WHITE TEE","options":[{"id":47657667,"name":"Default","price":29.0,"sold_out":false,"has_custom_price":false}],"shipping":[{"amount_alone":4.0,"amount_with_others":7.0,"country":{"id":42,"name":"United Kingdom","code":"GB"}},{"amount_alone":12.0,"amount_with_others":18.0}],"images":[{"url":"http://images.cdn.bigcartel.com/bigcartel/product_images/127226820/-/whtteefront.jpg","secure_url":"https://d1j5c7u4mzbpxw.cloudfront.net/bigcartel/product_images/127226820/-/whtteefront.jpg","width":1840,"height":2672}],"artists":[],"categories":[]},{"id":14710227,"name":"GREY TRACK PANT","permalink":"grey-track-pant","position":10,"price":36.0,"default_price":36.0,"tax":0.0,"url":"/product/grey-track-pant","status":"active","on_sale":false,"created_at":"2013-11-08T15:59:32.000Z","description":"GREY TRACK PANT","options":[{"id":47657985,"name":"Default","price":36.0,"sold_out":false,"has_custom_price":false}],"shipping":[{"amount_alone":5.0,"amount_with_others":8.0,"country":{"id":42,"name":"United Kingdom","code":"GB"}},{"amount_alone":15.0,"amount_with_others":23.0}],"images":[{"url":"http://images.cdn.bigcartel.com/bigcartel/product_images/127227063/-/greybottom.jpg","secure_url":"https://d1j5c7u4mzbpxw.cloudfront.net/bigcartel/product_images/127227063/-/greybottom.jpg","width":1424,"height":3512}],"artists":[],"categories":[]},{"id":14710209,"name":"BLACK TRACK PANT","permalink":"black-track-pant","position":11,"price":36.0,"default_price":36.0,"tax":0.0,"url":"/product/black-track-pant","status":"active","on_sale":false,"created_at":"2013-11-08T15:58:28.000Z","description":"BLACK TRACK PANT","options":[{"id":47657955,"name":"Default","price":36.0,"sold_out":false,"has_custom_price":false}],"shipping":[{"amount_alone":5.0,"amount_with_others":8.0,"country":{"id":42,"name":"United Kingdom","code":"GB"}},{"amount_alone":15.0,"amount_with_others":23.0}],"images":[{"url":"http://images.cdn.bigcartel.com/bigcartel/product_images/127226994/-/trackblkbottom.jpg","secure_url":"https://d1j5c7u4mzbpxw.cloudfront.net/bigcartel/product_images/127226994/-/trackblkbottom.jpg","width":1328,"height":3528}],"artists":[],"categories":[]}]