{"name":"kligraphic","description":"","url":"http://k7.bigcartel.com","website":null,"products_count":3,"currency":{"id":1,"sign":"$","name":"U.S. Dollar","code":"USD"},"country":{"id":84,"name":"Colombia","code":"CO"},"pages":[{"name":"About","permalink":"about"}],"categories":[{"id":5364546,"permalink":"albums","url":"/category/albums","name":"Albums"},{"id":5364549,"permalink":"hats","url":"/category/hats","name":"Hats"},{"id":5364552,"permalink":"prints","url":"/category/prints","name":"Prints"},{"id":5364555,"permalink":"tees","url":"/category/tees","name":"Tees"}],"artists":[]}