{"name":"El Rayo Taqueria","description":"Portland, Maine's award-winning taqueria serving authentic Mexican food! Call 780-TACO or visit us at 101 York St. (Corner of High Street) in Portland","url":"http://elrayotaqueria.bigcartel.com","website":"http://elrayotaqueria.com/","products_count":3,"currency":{"id":1,"sign":"$","name":"U.S. Dollar","code":"USD"},"country":{"id":43,"name":"United States","code":"US"},"pages":[],"categories":[{"id":2660523,"permalink":"gift-cards","url":"/category/gift-cards","name":"Gift Cards"},{"id":2660525,"permalink":"hats","url":"/category/hats","name":"Hats"},{"id":2660529,"permalink":"tees","url":"/category/tees","name":"Tees"}],"artists":[]}