{"name":"Daily Bread Market","description":null,"url":"http://dailybreadmarket.bigcartel.com","website":null,"products_count":1,"currency":{"id":1,"sign":"$","name":"U.S. Dollar","code":"USD"},"country":{"id":43,"name":"United States","code":"US"},"pages":[{"name":"FAQ","permalink":"faq"}],"categories":[{"id":95043,"permalink":"cds","url":"/category/cds","name":"CDs"},{"id":95044,"permalink":"hats","url":"/category/hats","name":"Hats"},{"id":95045,"permalink":"posters","url":"/category/posters","name":"Posters"},{"id":95046,"permalink":"tees","url":"/category/tees","name":"Tees"},{"id":95047,"permalink":"bags","url":"/category/bags","name":"Bags"}],"artists":[]}