{"name":"Craving for Chaos","description":null,"url":"http://cravingforchaos.bigcartel.com","website":"http://www.cravingforchaos.com","products_count":1,"currency":{"id":4,"sign":"&euro;","name":"Euro","code":"EUR"},"country":{"id":16,"name":"Germany","code":"DE"},"pages":[],"categories":[{"id":257048,"permalink":"cds","url":"/category/cds","name":"CDs"},{"id":257049,"permalink":"tickets","url":"/category/tickets","name":"Tickets"},{"id":257050,"permalink":"posters","url":"/category/posters","name":"Posters"},{"id":257051,"permalink":"tees","url":"/category/tees","name":"Tees"}],"artists":[]}